MANIFEST.in
README.md
setup.py
dbt/__init__.py
dbt/adapters/__init__.py
dbt/adapters/yugabytedb/__init__.py
dbt/adapters/yugabytedb/__version__.py
dbt/adapters/yugabytedb/column.py
dbt/adapters/yugabytedb/connections.py
dbt/adapters/yugabytedb/impl.py
dbt/adapters/yugabytedb/relation.py
dbt/adapters/yugabytedb/relation_configs/__init__.py
dbt/adapters/yugabytedb/relation_configs/constants.py
dbt/adapters/yugabytedb/relation_configs/index.py
dbt/adapters/yugabytedb/relation_configs/materialized_view.py
dbt/include/yugabytedb/__init__.py
dbt/include/yugabytedb/dbt_project.yml
dbt/include/yugabytedb/profile_template.yml
dbt/include/yugabytedb/sample_profiles.yml
dbt/include/yugabytedb/macros/adapters.sql
dbt/include/yugabytedb/macros/catalog.sql
dbt/include/yugabytedb/macros/relations.sql
dbt/include/yugabytedb/macros/timestamps.sql
dbt/include/yugabytedb/macros/materializations/incremental_strategies.sql
dbt/include/yugabytedb/macros/materializations/snapshot_merge.sql
dbt/include/yugabytedb/macros/relations/materialized_view/alter.sql
dbt/include/yugabytedb/macros/relations/materialized_view/create.sql
dbt/include/yugabytedb/macros/relations/materialized_view/describe.sql
dbt/include/yugabytedb/macros/relations/materialized_view/drop.sql
dbt/include/yugabytedb/macros/relations/materialized_view/refresh.sql
dbt/include/yugabytedb/macros/relations/materialized_view/rename.sql
dbt/include/yugabytedb/macros/relations/table/drop.sql
dbt/include/yugabytedb/macros/relations/table/rename.sql
dbt/include/yugabytedb/macros/relations/table/replace.sql
dbt/include/yugabytedb/macros/relations/view/drop.sql
dbt/include/yugabytedb/macros/relations/view/rename.sql
dbt/include/yugabytedb/macros/relations/view/replace.sql
dbt/include/yugabytedb/macros/utils/any_value.sql
dbt/include/yugabytedb/macros/utils/columns_spec_ddl.sql
dbt/include/yugabytedb/macros/utils/dateadd.sql
dbt/include/yugabytedb/macros/utils/datediff.sql
dbt/include/yugabytedb/macros/utils/last_day.sql
dbtx_yugabytedb.egg-info/PKG-INFO
dbtx_yugabytedb.egg-info/SOURCES.txt
dbtx_yugabytedb.egg-info/dependency_links.txt
dbtx_yugabytedb.egg-info/not-zip-safe
dbtx_yugabytedb.egg-info/requires.txt
dbtx_yugabytedb.egg-info/top_level.txt