Metadata-Version: 2.1
Name: dbtx-yugabytedb
Version: 1.7.8
Summary: The yugabytedb adapter plugin for dbt (data build tool)
Home-page: https://github.com/xangxiong/dbtx-yugabytedb
Author: Xang Xiong
Author-email: xang.xiong.email@gmail.com
License: UNKNOWN
Platform: UNKNOWN
Classifier: Development Status :: 5 - Production/Stable
Classifier: License :: OSI Approved :: Apache Software License
Classifier: Operating System :: Microsoft :: Windows
Classifier: Operating System :: MacOS :: MacOS X
Classifier: Operating System :: POSIX :: Linux
Classifier: Programming Language :: Python :: 3.8
Classifier: Programming Language :: Python :: 3.9
Classifier: Programming Language :: Python :: 3.10
Classifier: Programming Language :: Python :: 3.11
Requires-Python: >=3.8
